bilibili_dynamic/__init__.py
bilibili_dynamic/_version.py
bilibili_dynamic/DynamicRender.py
bilibili_dynamic/element/box-b.png
bilibili_dynamic/element/box.png
bilibili_dynamic/element/fm.png
bilibili_dynamic/element/hm.png
bilibili_dynamic/element/jianbian.png
bilibili_dynamic/element/link.png
bilibili_dynamic/element/off.png
bilibili_dynamic/element/om.png
bilibili_dynamic/element/tick.png
bilibili_dynamic/element/tick_A.png
bilibili_dynamic/element/tick_B.png
bilibili_dynamic/element/tv.png
bilibili_dynamic/element/user-auth.png
bilibili_dynamic/element/yy.png
bilibili_dynamic/format.py
bilibili_dynamic/initialize.py
bilibili_dynamic/network.py
bilibili_dynamic/textTools.py
bilibili_dynamic/typeface/CODE2000.ttf
bilibili_dynamic/typeface/NONT LICENSE
bilibili_dynamic/typeface/NotoColorEmoji.ttf
bilibili_dynamic/typeface/NotoSansCJKsc-Regular.otf
bilibili_dynamic/typeface/reserve/arial.ttf
bilibili_dynamic/typeface/reserve/himalaya.ttf
bilibili_dynamic/typeface/Unifont.ttf
bilibili_dynamic-0.0.8.dist-info/LICENSE
bilibili_dynamic-0.0.8.dist-info/WHEEL
bilibili_dynamic-0.0.8.dist-info/METADATA
bilibili_dynamic-0.0.8.dist-info/RECORD
